authorization_django/__init__.py
authorization_django/config.py
authorization_django/jwks.py
authorization_django/middleware.py
authorization_django/extensions/__init__.py
authorization_django/extensions/drf.py
authorization_django/extensions/scheme.py
datapunt_authorization_django-1.6.2.dist-info/licenses/LICENSE
datapunt_authorization_django-1.6.2.dist-info/METADATA
datapunt_authorization_django-1.6.2.dist-info/WHEEL
datapunt_authorization_django-1.6.2.dist-info/top_level.txt
datapunt_authorization_django-1.6.2.dist-info/RECORD
