Metadata-Version: 2.4
Name: datapunt-authorization-django
Version: 1.6.2
Summary: Datapunt authorization check for Django
Home-page: https://github.com/Amsterdam/authorization_django
Author: Amsterdam Datapunt
Author-email: datapunt@amsterdam.nl
License: Mozilla Public License Version 2.0
Classifier: Development Status :: 5 - Production/Stable
Classifier: Intended Audience :: Developers
Classifier: Natural Language :: English
Classifier: Topic :: System :: Systems Administration :: Authentication/Directory
Classifier: License :: OSI Approved :: Mozilla Public License 2.0 (MPL 2.0)
Classifier: Programming Language :: Python
Classifier: Programming Language :: Python :: 3.9
Classifier: Programming Language :: Python :: 3.10
Classifier: Programming Language :: Python :: 3.11
Classifier: Programming Language :: Python :: 3.12
License-File: LICENSE
Requires-Dist: Django>=4.2
Requires-Dist: requests>=2.32.3
Requires-Dist: jwcrypto>=1.5.6
Provides-Extra: tests
Requires-Dist: pytest>=8.3.5; extra == "tests"
Requires-Dist: pytest-cov>=6.0.0; extra == "tests"
Requires-Dist: pytest-django>=4.10.0; extra == "tests"
Requires-Dist: requests_mock; extra == "tests"
Provides-Extra: extended
Requires-Dist: djangorestframework>=3.15.2; extra == "extended"
Requires-Dist: drf-spectacular>=0.28.0; extra == "extended"
Requires-Dist: pytest>=8.3.5; extra == "extended"
Requires-Dist: pytest-cov>=6.0.0; extra == "extended"
Requires-Dist: pytest-django>=4.10.0; extra == "extended"
Requires-Dist: requests_mock; extra == "extended"
Dynamic: author
Dynamic: author-email
Dynamic: classifier
Dynamic: description
Dynamic: description-content-type
Dynamic: home-page
Dynamic: license
Dynamic: license-file
Dynamic: provides-extra
Dynamic: requires-dist
Dynamic: summary
